jsonschema2rst/__init__.py
jsonschema2rst/indexer.py
jsonschema2rst/json_pointer_util.py
jsonschema2rst/parser.py
jsonschema2rst/parser_runner.py
jsonschema2rst/rst_utils.py
jsonschema2rst/rst_writer.py
jsonschema2rst/tree_node.py
jsonschema2rst-0.1.7.dist-info/AUTHORS
jsonschema2rst-0.1.7.dist-info/LICENSE.txt
jsonschema2rst-0.1.7.dist-info/METADATA
jsonschema2rst-0.1.7.dist-info/WHEEL
jsonschema2rst-0.1.7.dist-info/entry_points.txt
jsonschema2rst-0.1.7.dist-info/top_level.txt
jsonschema2rst-0.1.7.dist-info/RECORD
