Metadata-Version: 2.1
Name: jsonschema2rst
Version: 0.1.7
Summary: Parser for yaml/json schemas to rst
Home-page: https://github.com/inspirehep/jsonschema2rst
Author: CERN
Author-email: admin@inspirehep.net
License: GPLv2
Keywords: jsonschema yaml rst parser documentation
License-File: LICENSE.txt
License-File: AUTHORS
Requires-Dist: pyyaml<7.0,>=6.0
Requires-Dist: six
Provides-Extra: tests
Requires-Dist: coverage>=4.0; extra == "tests"
Requires-Dist: isort<5.0.0; extra == "tests"
Requires-Dist: pytest-cache>=1.0; extra == "tests"
Requires-Dist: pytest-cov>=1.8.0; extra == "tests"
Requires-Dist: pytest-pep8>=1.0.6; extra == "tests"
Requires-Dist: pytest<6.0.0; extra == "tests"
Requires-Dist: mock>=2.0.0; extra == "tests"
